darwin_mendel/__init__.py
darwin_mendel/optimize_dtc.py
darwin_mendel/optimize_dtr.py
darwin_mendel/optimize_lgbmc.py
darwin_mendel/optimize_lgbmr.py
darwin_mendel/optimize_rfc.py
darwin_mendel/optimize_rfr.py
darwin_mendel/optimize_xgbc.py
darwin_mendel/optimize_xgbr.py
darwin_mendel-0.2.4.dist-info/LICENSE
darwin_mendel-0.2.4.dist-info/METADATA
darwin_mendel-0.2.4.dist-info/WHEEL
darwin_mendel-0.2.4.dist-info/top_level.txt
darwin_mendel-0.2.4.dist-info/RECORD
